{
    "amethyst": {
        "sha256": "16n5vdyjs6m4saqibv3fb420w6x83lsiw182qm3prnilh4q9qld3",
        "type": "file",
        "url": "https://github.com/ianyh/Amethyst/releases/download/v0.15.4/Amethyst.zip",
        "url_template": "https://github.com/ianyh/Amethyst/releases/download/v<version>/Amethyst.zip",
        "version": "0.15.4"
    },
    "any-jump.vim": {
        "branch": "master",
        "description": "Jump to any definition and references 👁 IDE madness without overhead 🚀",
        "homepage": "",
        "owner": "pechorin",
        "repo": "any-jump.vim",
        "rev": "c5c319fdf588c9ed53e6a32eb2608bd1eb2f9c92",
        "sha256": "1lzpr5x7zvpc252j6ipp2rfjfd25a0mrkikq8vdsbxbamp8cyqpb",
        "type": "tarball",
        "url": "https://github.com/pechorin/any-jump.vim/archive/c5c319fdf588c9ed53e6a32eb2608bd1eb2f9c92.tar.gz",
        "url_template": "https://github.com/<owner>/<repo>/archive/<rev>.tar.gz"
    },
    "complete-alias": {
        "branch": "master",
        "description": "automagical shell alias completion;",
        "homepage": "https://repo.cykerway.com/complete-alias",
        "owner": "cykerway",
        "repo": "complete-alias",
        "rev": "7525b8f35796afda17ddba620a0c6edf246902b8",
        "sha256": "1s0prdnmb2qnzc8d7ddldzqa53yc10qq0lbgx2l9dzmz8pdwylyc",
        "type": "tarball",
        "url": "https://github.com/cykerway/complete-alias/archive/7525b8f35796afda17ddba620a0c6edf246902b8.tar.gz",
        "url_template": "https://github.com/<owner>/<repo>/archive/<rev>.tar.gz"
    },
    "context.vim": {
        "branch": "master",
        "description": "Vim plugin that shows the context of the currently visible buffer contents",
        "homepage": null,
        "owner": "wellle",
        "repo": "context.vim",
        "rev": "e38496f1eb5bb52b1022e5c1f694e9be61c3714c",
        "sha256": "1iy614py9qz4rwk9p4pr1ci0m1lvxil0xiv3ymqzhqrw5l55n346",
        "type": "tarball",
        "url": "https://github.com/wellle/context.vim/archive/e38496f1eb5bb52b1022e5c1f694e9be61c3714c.tar.gz",
        "url_template": "https://github.com/<owner>/<repo>/archive/<rev>.tar.gz"
    },
    "dmg-brave": {
        "sha256": "0laybmncy83dadmlz2a01qfq1d5nn43jwrdcmjk3ga5swfb0hh7d",
        "type": "file",
        "url": "https://github.com/brave/brave-browser/releases/download/v1.24.86/Brave-Browser-universal.dmg",
        "url_template": "https://github.com/brave/brave-browser/releases/download/v<version>/Brave-Browser-universal.dmg",
        "version": "1.24.86"
    },
    "dmg-discord": {
        "sha256": "1afb0qj23hmhsz9jgzwaj5gqsxdwdxi8bcc656s27qhydnbxbgpn",
        "type": "file",
        "url": "https://dl.discordapp.net/apps/osx/0.0.261/Discord.dmg",
        "url_template": "https://dl.discordapp.net/apps/osx/<version>/Discord.dmg",
        "version": "0.0.261"
    },
    "dmg-firefox": {
        "sha256": "0z9p6jng7is8pq21dffjr6mfk81q08v99fwmhj22g9b1miqxrvcz",
        "type": "file",
        "url": "https://download-installer.cdn.mozilla.net/pub/firefox/releases/88.0.1/mac/en-US/Firefox%2088.0.1.dmg",
        "url_template": "https://download-installer.cdn.mozilla.net/pub/firefox/releases/<version>/mac/en-US/Firefox%20<version>.dmg",
        "version": "88.0.1"
    },
    "dmg-signal-desktop": {
        "sha256": "0fhx2k42p4cvfm7d2l8rvivr3s969rc9zlhnysg22a9y7l0cs9w3",
        "type": "file",
        "url": "https://updates.signal.org/desktop/signal-desktop-mac-5.3.0.dmg",
        "url_template": "https://updates.signal.org/desktop/signal-desktop-mac-<version>.dmg",
        "version": "5.3.0"
    },
    "dmg-spotify": {
        "sha256": "0mixjdsbrn9bymbicm5s1qd5wfzi4qa4qc4jwwx5ifpiqrkjlk3q",
        "type": "file",
        "url": "https://download.scdn.co/Spotify-0.8.5.dmg",
        "url_template": "https://download.scdn.co/Spotify-<version>.dmg",
        "version": "0.8.5"
    },
    "evilhack": {
        "branch": "master",
        "description": "A variant of NetHack that is designed to be a much more challenging experience than the original, drawing inspiration and content from various existing variants along with adding unique and never-before-seen custom content.",
        "homepage": "",
        "owner": "k21971",
        "repo": "EvilHack",
        "rev": "97b55a21e8d26dc76e7ab175ba6fab3bab4ba6aa",
        "sha256": "1za8pkqsf2x1d7ss5vvg7nhpf4139mln3gbvg7zgmr1ipg0mjg88",
        "type": "tarball",
        "url": "https://github.com/k21971/EvilHack/archive/97b55a21e8d26dc76e7ab175ba6fab3bab4ba6aa.tar.gz",
        "url_template": "https://github.com/<owner>/<repo>/archive/<rev>.tar.gz"
    },
    "flake-compat": {
        "branch": "master",
        "description": null,
        "homepage": null,
        "owner": "edolstra",
        "repo": "flake-compat",
        "rev": "99f1c2157fba4bfe6211a321fd0ee43199025dbf",
        "sha256": "0x2jn3vrawwv9xp15674wjz9pixwjyj3j771izayl962zziivbx2",
        "type": "tarball",
        "url": "https://github.com/edolstra/flake-compat/archive/99f1c2157fba4bfe6211a321fd0ee43199025dbf.tar.gz",
        "url_template": "https://github.com/<owner>/<repo>/archive/<rev>.tar.gz"
    },
    "git-fuzzy": {
        "branch": "master",
        "description": "interactive `git` with the help of `fzf`",
        "homepage": "",
        "owner": "bigH",
        "repo": "git-fuzzy",
        "rev": "c4077ec89c1fa8d74666d8c3c51a483890a6461d",
        "sha256": "0igiaqv6r5r0m93s7s1pfq7fnz5cswpp7cwwc3dnwh3v6fcjhwvd",
        "type": "tarball",
        "url": "https://github.com/bigH/git-fuzzy/archive/c4077ec89c1fa8d74666d8c3c51a483890a6461d.tar.gz",
        "url_template": "https://github.com/<owner>/<repo>/archive/<rev>.tar.gz"
    },
    "git-trim": {
        "branch": "master",
        "description": "Utility to delete git branches interactively",
        "homepage": null,
        "owner": "dstnbrkr",
        "repo": "git-trim",
        "rev": "68322f146a443937e8f59aab4fa3dd0eb976a4db",
        "sha256": "1y1z6hzfhs42pwkhwfa8qh1508rhx23idnnq1zmaabxyjkh42v01",
        "type": "tarball",
        "url": "https://github.com/dstnbrkr/git-trim/archive/68322f146a443937e8f59aab4fa3dd0eb976a4db.tar.gz",
        "url_template": "https://github.com/<owner>/<repo>/archive/<rev>.tar.gz"
    },
    "inlets": {
        "branch": "master",
        "description": "Cloud Native Tunnel for APIs",
        "homepage": "https://docs.inlets.dev",
        "owner": "inlets",
        "repo": "inlets",
        "rev": "b8f1dcdcd85978f1692019dbc907471720eb2aa5",
        "sha256": "0lzrnfvm0gwm0dmk3xqr6hkhqcssvbaw9wpdgr1i2cyil61f01i2",
        "type": "tarball",
        "url": "https://github.com/inlets/inlets/archive/b8f1dcdcd85978f1692019dbc907471720eb2aa5.tar.gz",
        "url_template": "https://github.com/<owner>/<repo>/archive/<rev>.tar.gz"
    },
    "jsonc.vim": {
        "branch": "master",
        "description": "jsonc syntax support for vim",
        "homepage": null,
        "owner": "neoclide",
        "repo": "jsonc.vim",
        "rev": "63ffa5199a0e64d5ce0515256407f32dfbd67fc3",
        "sha256": "047c2sc8q49axhi9416lzzpv5ykczc63dqd4xy56rfcfrvsi199j",
        "type": "tarball",
        "url": "https://github.com/neoclide/jsonc.vim/archive/63ffa5199a0e64d5ce0515256407f32dfbd67fc3.tar.gz",
        "url_template": "https://github.com/<owner>/<repo>/archive/<rev>.tar.gz"
    },
    "juicefs": {
        "branch": "v0.10.0",
        "description": "JuiceFS is a distributed POSIX file system built on top of Redis and S3.",
        "homepage": "",
        "owner": "juicedata",
        "repo": "juicefs",
        "rev": "4c56261884f432535be2d006ba8b8472e59774cd",
        "sha256": "185a1c8a1v0sn869x9y5ipcam3l1bll1pim9ws2vsv4lkmghi03q",
        "type": "tarball",
        "url": "https://github.com/juicedata/juicefs/archive/4c56261884f432535be2d006ba8b8472e59774cd.tar.gz",
        "url_template": "https://github.com/<owner>/<repo>/archive/<rev>.tar.gz"
    },
    "nixos-18_09": {
        "sha256": "0f3y936zqblzvl76gpd9awamfyxxqck3y6z82hsq50d3bmb779zx",
        "type": "tarball",
        "url": "https://releases.nixos.org/nixos/18.09/nixos-18.09.2574.a7e559a5504/nixexprs.tar.xz",
        "url_template": "https://releases.nixos.org/nixos/18.09/<version>/nixexprs.tar.xz",
        "version": "nixos-18.09.2574.a7e559a5504"
    },
    "nixos-20_09": {
        "sha256": "0n2i0pdhkwyclx502h2n2q1hll6iyczk0airzbkg5inla2bivf7d",
        "type": "tarball",
        "url": "https://releases.nixos.org/nixos/20.09/nixos-20.09.4232.8f014925190/nixexprs.tar.xz",
        "url_template": "https://releases.nixos.org/nixos/20.09/<version>/nixexprs.tar.xz",
        "version": "nixos-20.09.4232.8f014925190"
    },
    "nixos-unstable": {
        "sha256": "0gnz9dfh6gryi51m91gxz8cd4449mzp0d90g2yccxxai9v543489",
        "type": "tarball",
        "url": "https://releases.nixos.org/nixos/unstable/nixos-21.11pre292520.540dccb2aea/nixexprs.tar.xz",
        "url_template": "https://releases.nixos.org/nixos/unstable/<version>/nixexprs.tar.xz",
        "version": "nixos-21.11pre292520.540dccb2aea"
    },
    "nixpkgs-bundler1": {
        "branch": "96a1dbac972c4f67aea7ee548f4e5531003f8ab0",
        "description": "Nix Packages collection",
        "homepage": null,
        "owner": "NixOS",
        "repo": "nixpkgs",
        "rev": "96a1dbac972c4f67aea7ee548f4e5531003f8ab0",
        "sha256": "0mx335ym9ai3ci3dgwszk289xjpvsqf6xx6g43250y5zwz9692mz",
        "type": "tarball",
        "url": "https://github.com/NixOS/nixpkgs/archive/96a1dbac972c4f67aea7ee548f4e5531003f8ab0.tar.gz",
        "url_template": "https://github.com/<owner>/<repo>/archive/<rev>.tar.gz"
    },
    "pynixify": {
        "branch": "main",
        "description": "Nix expression generator for Python projects",
        "homepage": null,
        "owner": "cript0nauta",
        "repo": "pynixify",
        "rev": "140ec9aa7061383aa0d6a45969f6ef4f6570acb4",
        "sha256": "06rsxrbxwqb8w71vx6w0v09fpisavifia4y7dx9yfj3n601y3rvj",
        "type": "tarball",
        "url": "https://github.com/cript0nauta/pynixify/archive/140ec9aa7061383aa0d6a45969f6ef4f6570acb4.tar.gz",
        "url_template": "https://github.com/<owner>/<repo>/archive/<rev>.tar.gz"
    },
    "ranger_devicons": {
        "branch": "main",
        "description": "Ranger plugin that adds file glyphs / icon support to Ranger",
        "homepage": "",
        "owner": "alexanderjeurissen",
        "repo": "ranger_devicons",
        "rev": "e02b6a3203411b76616a0e4328245bf8b47c5dcc",
        "sha256": "19b06p3icpb214kpbf7irlyy813ax12i2jhibhxd2nflz9n66pg9",
        "type": "tarball",
        "url": "https://github.com/alexanderjeurissen/ranger_devicons/archive/e02b6a3203411b76616a0e4328245bf8b47c5dcc.tar.gz",
        "url_template": "https://github.com/<owner>/<repo>/archive/<rev>.tar.gz"
    },
    "slapper": {
        "branch": "master",
        "description": "Simple load testing tool with real-time updated histogram of request timings",
        "homepage": "",
        "owner": "ikruglov",
        "repo": "slapper",
        "rev": "552f8a34ae9ff4c74dfa7c83c62cda6028ae2f29",
        "sha256": "0zaz30mkmnahvv79j59bx1c6d6l9i0729qqfbmijpr44h8q5gxvk",
        "type": "tarball",
        "url": "https://github.com/ikruglov/slapper/archive/552f8a34ae9ff4c74dfa7c83c62cda6028ae2f29.tar.gz",
        "url_template": "https://github.com/<owner>/<repo>/archive/<rev>.tar.gz"
    },
    "vim-anyfold": {
        "branch": "master",
        "description": "Language agnostic vim plugin for folding and motion based on indentation.",
        "homepage": "",
        "owner": "pseewald",
        "repo": "vim-anyfold",
        "rev": "3ed5d8ccbf0f5031f7c7d2be05aa7ddb4550dc5c",
        "sha256": "14grfm5vra2lrnilsf6gbfmvn6v4pbi1l94ac713qac592fjq5kv",
        "type": "tarball",
        "url": "https://github.com/pseewald/vim-anyfold/archive/3ed5d8ccbf0f5031f7c7d2be05aa7ddb4550dc5c.tar.gz",
        "url_template": "https://github.com/<owner>/<repo>/archive/<rev>.tar.gz"
    },
    "yarn-completion": {
        "branch": "master",
        "description": "Bash completion for Yarn",
        "homepage": "",
        "owner": "dsifford",
        "repo": "yarn-completion",
        "rev": "5bf2968493a7a76649606595cfca880a77e6ac0e",
        "sha256": "1w1df1cvf3c1maq60kx927x7x9zmb40n02pfgf3ynaai5n398195",
        "type": "tarball",
        "url": "https://github.com/dsifford/yarn-completion/archive/5bf2968493a7a76649606595cfca880a77e6ac0e.tar.gz",
        "url_template": "https://github.com/<owner>/<repo>/archive/<rev>.tar.gz"
    }
}
